{
  "version": "0.2",
  "$schema": "https://raw.githubusercontent.com/streetsidesoftware/cspell/main/cspell.schema.json",
  "language": "en",
  "words": [
    "addrs",
    "Appstore",
    "checkpointing",
    "chenglong",
    "clickhouse",
    "Dingtalk",
    "flink",
    "fullpage",
    "geekblue",
    "hdfs",
    "inlines",
    "Intls",
    "kiro",
    "Mbps",
    "nodrag",
    "nopan",
    "paimon",
    "Popconfirm",
    "reactflow",
    "rocksdb",
    "sider",
    "Subflow",
    "sysconfig",
    "Wechat",
    "xyflow",
    "postgresql",
    "sqlserver",
    "cspell"
  ],
  "ignorePaths": [
    ".git",
    "cspell.json",
    "*.{log,svg,snap,png}",
    "node_modules/**",
    "dist/**",
    "package-lock.json",
    "*.tsbuildinfo"
  ]
}
